LICENSE
MANIFEST.in
README.md
setup.cfg
setup.py
cloudbenchmark/__init__.py
cloudbenchmark/ansible_manager.py
cloudbenchmark/benchmark_jobs.py
cloudbenchmark/benchmarkrecorder.py
cloudbenchmark/cloudformation_manager.py
cloudbenchmark/deploy_manager.py
cloudbenchmark/keypair_manager.py
cloudbenchmark/main.py
cloudbenchmark/make_yaml.py
cloudbenchmark/s3benchmark.py
cloudbenchmark/utils.py
cloudbenchmark.egg-info/PKG-INFO
cloudbenchmark.egg-info/SOURCES.txt
cloudbenchmark.egg-info/dependency_links.txt
cloudbenchmark.egg-info/entry_points.txt
cloudbenchmark.egg-info/requires.txt
cloudbenchmark.egg-info/top_level.txt
cloudbenchmark/config/condition_patterns.yaml
cloudbenchmark/config/test_set_list.yaml
cloudbenchmark/playbook/install.yaml
cloudbenchmark/template/ec2.yaml